Metadata-Version: 2.1
Name: random-quote-generator
Version: 2.0.0
Summary: 
Author: Jan Giacomelli
Author-email: jan@typless.com
Requires-Python: >=3.7,<4.0
Classifier: Programming Language :: Python :: 3
Classifier: Programming Language :: Python :: 3.7
Classifier: Programming Language :: Python :: 3.8
Classifier: Programming Language :: Python :: 3.9
Requires-Dist: pytest-cov (>=2.10.1,<3.0.0)
